<ProceduresDB build="By jojo2357, with FAA data. Data factor = 0.7132">
	<Airport ICAOcode="KGYY">
		<Sid Name="ADELL6">
		</Sid>
		<Sid Name="BLOKR6">
		</Sid>
		<Sid Name="CARYN6">
		</Sid>
		<Sid Name="DARCY6">
		</Sid>
		<Sid Name="ELANR6">
		</Sid>
		<Star Name="GSH9">
		</Star>
		<Star Name="LUCIT2">
		</Star>
		<Star Name="MOTIF6">
		</Star>
		<Approach Name="RNVZ12">
		</Approach>
		<Approach Name="RNVZ30">
		</Approach>
		<Approach Name="ILS30">
		</Approach>
		<Approach Name="VDM30">
		</Approach>
		<Approach Name="RNV02">
		</Approach>
		<Approach Name="RNVY12">
		</Approach>
		<Approach Name="RNV20">
		</Approach>
		<Approach Name="RNVY30">
		</Approach>
	</Airport>
</ProceduresDB>
