<ProceduresDB build="By jojo2357, with FAA data. Data factor = 0.7132">
	<Airport ICAOcode="KORL">
		<Sid Name="NYTES1">
		</Sid>
		<Sid Name="TOLLZ1">
		</Sid>
		<Star Name="ALYNA3">
		</Star>
		<Star Name="GOOFY7">
		</Star>
		<Star Name="JAFAR3">
		</Star>
		<Star Name="JOKRS3">
		</Star>
		<Star Name="LEESE3">
		</Star>
		<Star Name="MINEE5">
		</Star>
		<Star Name="PRICY3">
		</Star>
		<Star Name="RIDES2">
		</Star>
		<Star Name="SHREK2">
		</Star>
		<Star Name="TTHOR3">
		</Star>
		<Approach Name="ILS07">
		</Approach>
		<Approach Name="ILS25">
		</Approach>
		<Approach Name="VDM07">
		</Approach>
		<Approach Name="VDM25">
		</Approach>
		<Approach Name="RNV07">
		</Approach>
		<Approach Name="RNV25">
		</Approach>
	</Airport>
</ProceduresDB>
